lm_dw_deezer/__init__.py
lm_dw_deezer/compressions/__init__.py
lm_dw_deezer/compressions/gzip.py
lm_dw_deezer/compressions/utils.py
lm_dw_deezer/compressions/zip.py
lm_dw_deezer/compressions/zstd.py
lm_dw_deezer/config/__init__.py
lm_dw_deezer/config/conf.py
lm_dw_deezer/config/enums.py
lm_dw_deezer/config/image.py
lm_dw_deezer/config/thread_func.py
lm_dw_deezer/config/utils.py
lm_dw_deezer/config/utils_infos.py
lm_dw_deezer/decrypt/__init__.py
lm_dw_deezer/decrypt/decryptor.py
lm_dw_deezer/decrypt/utils.py
lm_dw_deezer/decrypt/utils_infos.py
lm_dw_deezer/dw.py
lm_dw_deezer/dw_helpers/__init__.py
lm_dw_deezer/dw_helpers/album.py
lm_dw_deezer/dw_helpers/dws.py
lm_dw_deezer/dw_helpers/playlist.py
lm_dw_deezer/dw_helpers/track.py
lm_dw_deezer/dw_helpers/utils.py
lm_dw_deezer/dw_helpers/utils_infos.py
lm_dw_deezer/dw_utils.py
lm_dw_deezer/exceptions/__init__.py
lm_dw_deezer/exceptions/no_be.py
lm_dw_deezer/exceptions/no_stream_data.py
lm_dw_deezer/exes/cli.py
lm_dw_deezer/exes/data_utils.py
lm_dw_deezer/exes/read_browsers_cookies.py
lm_dw_deezer/exes/utils.py
lm_dw_deezer/generators/__init__.py
lm_dw_deezer/generators/album.py
lm_dw_deezer/generators/playlist.py
lm_dw_deezer/generators/track.py
lm_dw_deezer/graphql/__init__.py
lm_dw_deezer/graphql/queries.py
lm_dw_deezer/graphql/types.py
lm_dw_deezer/logger.py
lm_dw_deezer/medjays/__init__.py
lm_dw_deezer/py.typed
lm_dw_deezer/tagger/__init__.py
lm_dw_deezer/tagger/helpers.py
lm_dw_deezer/tagger/tag_flac.py
lm_dw_deezer/tagger/tag_mp3.py
lm_dw_deezer/tagger/tag_track.py
lm_dw_deezer/tagger/utils_infos.py
lm_dw_deezer/types/__init__.py
lm_dw_deezer/types/data_utils.py
lm_dw_deezer/types/dw_album.py
lm_dw_deezer/types/dw_playlist.py
lm_dw_deezer/types/dw_track.py
lm_dw_deezer/types/enums.py
lm_dw_deezer/types/pipe_ext/__init__.py
lm_dw_deezer/types/pipe_ext/album.py
lm_dw_deezer/types/pipe_ext/bases.py
lm_dw_deezer/types/pipe_ext/playlist.py
lm_dw_deezer/types/pipe_ext/track.py
lm_dw_deezer/types/pipe_ext/tracks.py
lm_dw_deezer-0.0.2b10.dist-info/METADATA
lm_dw_deezer-0.0.2b10.dist-info/WHEEL
lm_dw_deezer-0.0.2b10.dist-info/entry_points.txt
lm_dw_deezer-0.0.2b10.dist-info/RECORD
