Metadata-Version: 2.1
Name: lm-dw-deezer
Version: 0.0.2b10
Summary: Liberum Melodian Library for making easy tracks downloading from Deezer
Home-page: https://github.com/An0nimia/lm_dw_deezer
License: CC BY 4.0
Author: An0nimia
Author-email: an0nimia@protonmail.com
Requires-Python: >=3.12,<4.0
Classifier: License :: Other/Proprietary License
Classifier: Programming Language :: Python :: 3
Classifier: Programming Language :: Python :: 3.12
Provides-Extra: rustdw
Requires-Dist: api-deezer-full (>=0.0.1b37,<0.0.2)
Requires-Dist: inquirerpy (==0.3.4)
Requires-Dist: lm-deezer-bf-dec (>=0.0.1b3,<0.0.2) ; extra == "rustdw"
Requires-Dist: mutagen (>=1.47.0,<2.0.0)
Requires-Dist: pycryptodomex (>=3.20.0,<4.0.0)
Requires-Dist: pydantic (>=2.4.1,<3.0.0)
Requires-Dist: requests (>=2.32.0,<3.0.0)
Requires-Dist: tqdm (>=4.66.3,<5.0.0)
Requires-Dist: typer[all] (>=0.9.0,<0.10.0)
Requires-Dist: zstandard (>=0.22.0,<0.23.0)
Project-URL: Repository, https://github.com/An0nimia/lm_dw_deezer
